{"circuit": {"vertex_list": [0, 33, 35, 67, 68, 113, 121, 123, 124, 125, 126, 130, 146, 148, 149, 150, 151, 205, 233, 254, 255, 256, 292, 297, 298, 318, 320, 321, 322, 327, 328, 333, 334, 335, 336, 1, 18, 21, 22, 23, 47, 48, 49, 50, 66, 69, 88, 90, 97, 98, 99, 100, 176, 178, 253, 257, 274, 275, 279, 280, 281, 282, 305, 307, 2, 20, 31, 34, 40, 64, 70, 83, 107, 188, 206, 228, 242, 243, 244, 267, 268, 269, 271, 306, 308, 3, 29, 36, 41, 58, 62, 72, 84, 86, 102, 104, 118, 127, 134, 143, 153, 155, 162, 174, 177, 185, 186, 189, 198, 199, 207, 232, 236, 238, 239, 241, 252, 258, 260, 283, 304, 309, 314, 339, 4, 32, 37, 63, 71, 80, 108, 114, 132, 139, 158, 200, 201, 202, 203, 204, 208, 209, 210, 211, 212, 213, 214, 215, 216, 217, 218, 219, 220, 221, 222, 223, 224, 225, 226, 227, 229, 230, 231, 251, 259, 294, 302, 311, 313, 5, 30, 38, 53, 56, 65, 74, 92, 94, 96, 101, 103, 105, 137, 145, 147, 152, 154, 156, 175, 180, 329, 332, 337, 338, 6, 61, 73, 78, 109, 115, 119, 122, 128, 129, 131, 141, 159, 172, 179, 247, 250, 7, 60, 75, 91, 95, 106, 110, 116, 135, 142, 144, 157, 160, 170, 181, 240, 273, 276, 277, 278, 284, 285, 286, 289, 324, 326, 341, 8, 43, 51, 52, 54, 81, 82, 85, 87, 93, 111, 140, 161, 164, 165, 166, 192, 194, 195, 249, 261, 262, 290, 303, 310, 319, 331, 340, 342, 9, 27, 44, 59, 76, 117, 120, 133, 136, 173, 182, 248, 263, 270, 272, 287, 288, 299, 300, 315, 316, 330, 343, 10, 28, 39, 112, 138, 266, 291, 301, 312, 11, 25, 42, 57, 77, 171, 184, 12, 26, 45, 168, 183, 190, 193, 197, 234, 235, 237, 245, 265, 295, 296, 323, 325, 13, 19, 89, 169, 187, 14, 24, 46, 55, 79, 167, 191, 246, 264, 293, 317, 15, 16, 163, 196, 17], "hyperedge_list": [{"vertices": [0, 33], "weight": 1}, {"vertices": [0, 35], "weight": 1}, {"vertices": [0, 67], "weight": 1}, {"vertices": [0, 68], "weight": 1}, {"vertices": [0, 113, 121, 123], "weight": 1}, {"vertices": [0, 124, 125, 126, 130, 146, 148], "weight": 1}, {"vertices": [0, 149, 150, 151], "weight": 1}, {"vertices": [0, 205, 233], "weight": 1}, {"vertices": [0, 254], "weight": 1}, {"vertices": [0, 255, 256, 292, 297], "weight": 1}, {"vertices": [0, 298, 318], "weight": 1}, {"vertices": [0, 320, 321, 322], "weight": 1}, {"vertices": [0, 327, 328, 333], "weight": 1}, {"vertices": [0, 334, 335, 336], "weight": 1}, {"vertices": [1, 18, 21, 22], "weight": 1}, {"vertices": [1, 23, 47], "weight": 1}, {"vertices": [1, 48, 49, 50, 66], "weight": 1}, {"vertices": [1, 67, 68], "weight": 1}, {"vertices": [1, 69], "weight": 1}, {"vertices": [1, 88, 90, 97], "weight": 1}, {"vertices": [1, 98, 99, 100], "weight": 1}, {"vertices": [1, 176], "weight": 1}, {"vertices": [1, 178, 253], "weight": 1}, {"vertices": [1, 254, 255], "weight": 1}, {"vertices": [1, 257, 274, 275, 279], "weight": 1}, {"vertices": [1, 280, 281, 282], "weight": 1}, {"vertices": [1, 305], "weight": 1}, {"vertices": [1, 307], "weight": 1}, {"vertices": [2, 20, 31], "weight": 1}, {"vertices": [2, 34, 40], "weight": 1}, {"vertices": [2, 64], "weight": 1}, {"vertices": [2, 66, 69], "weight": 1}, {"vertices": [2, 70, 83], "weight": 1}, {"vertices": [2, 88, 100], "weight": 1}, {"vertices": [2, 107], "weight": 1}, {"vertices": [2, 113, 126], "weight": 1}, {"vertices": [2, 130, 151, 188, 206], "weight": 1}, {"vertices": [2, 228, 242, 243], "weight": 1}, {"vertices": [2, 244, 267], "weight": 1}, {"vertices": [2, 268, 269, 271], "weight": 1}, {"vertices": [2, 274, 282, 306], "weight": 1}, {"vertices": [2, 308], "weight": 1}, {"vertices": [2, 327, 336], "weight": 1}, {"vertices": [3, 29], "weight": 1}, {"vertices": [3, 31, 34], "weight": 1}, {"vertices": [3, 36], "weight": 1}, {"vertices": [3, 41, 58], "weight": 1}, {"vertices": [3, 62, 72], "weight": 1}, {"vertices": [3, 84, 86], "weight": 1}, {"vertices": [3, 90, 99], "weight": 1}, {"vertices": [3, 102, 104], "weight": 1}, {"vertices": [3, 118], "weight": 1}, {"vertices": [3, 121, 125], "weight": 1}, {"vertices": [3, 127, 134, 143], "weight": 1}, {"vertices": [3, 146, 150], "weight": 1}, {"vertices": [3, 153, 155], "weight": 1}, {"vertices": [3, 162, 174], "weight": 1}, {"vertices": [3, 177, 185, 186], "weight": 1}, {"vertices": [3, 189], "weight": 1}, {"vertices": [3, 198, 199], "weight": 1}, {"vertices": [3, 207, 232], "weight": 1}, {"vertices": [3, 236, 238], "weight": 1}, {"vertices": [3, 239], "weight": 1}, {"vertices": [3, 241], "weight": 1}, {"vertices": [3, 252], "weight": 1}, {"vertices": [3, 253, 257], "weight": 1}, {"vertices": [3, 258, 260], "weight": 1}, {"vertices": [3, 275, 281], "weight": 1}, {"vertices": [3, 283], "weight": 1}, {"vertices": [3, 304], "weight": 1}, {"vertices": [3, 306, 308], "weight": 1}, {"vertices": [3, 309, 314], "weight": 1}, {"vertices": [3, 328, 335], "weight": 1}, {"vertices": [3, 339], "weight": 1}, {"vertices": [4, 32], "weight": 1}, {"vertices": [4, 33, 35], "weight": 1}, {"vertices": [4, 37], "weight": 1}, {"vertices": [4, 41, 63], "weight": 1}, {"vertices": [4, 64, 70], "weight": 1}, {"vertices": [4, 71, 72], "weight": 1}, {"vertices": [4, 80], "weight": 1}, {"vertices": [4, 86, 102], "weight": 1}, {"vertices": [4, 108], "weight": 1}, {"vertices": [4, 114], "weight": 1}, {"vertices": [4, 118, 127], "weight": 1}, {"vertices": [4, 132], "weight": 1}, {"vertices": [4, 139], "weight": 1}, {"vertices": [4, 143, 153], "weight": 1}, {"vertices": [4, 158, 186, 188, 200, 201, 202, 203, 204], "weight": 1}, {"vertices": [4, 205, 206, 207, 208, 209, 210, 211, 212, 213, 214, 215, 216], "weight": 1}, {"vertices": [4, 217, 218, 219, 220, 221, 222, 223, 224], "weight": 1}, {"vertices": [4, 225, 226, 227, 229, 230, 231, 232, 233, 241], "weight": 1}, {"vertices": [4, 251], "weight": 1}, {"vertices": [4, 252, 258], "weight": 1}, {"vertices": [4, 259, 260, 283], "weight": 1}, {"vertices": [4, 294, 302], "weight": 1}, {"vertices": [4, 304, 309], "weight": 1}, {"vertices": [4, 311, 313, 314, 339], "weight": 1}, {"vertices": [5, 20, 30], "weight": 1}, {"vertices": [5, 32, 37], "weight": 1}, {"vertices": [5, 38, 40, 53, 56], "weight": 1}, {"vertices": [5, 58, 62], "weight": 1}, {"vertices": [5, 65, 74], "weight": 1}, {"vertices": [5, 92, 94, 96], "weight": 1}, {"vertices": [5, 97, 98], "weight": 1}, {"vertices": [5, 101, 103, 105, 137, 145, 147], "weight": 1}, {"vertices": [5, 148, 149], "weight": 1}, {"vertices": [5, 152, 154, 156, 175], "weight": 1}, {"vertices": [5, 176, 178], "weight": 1}, {"vertices": [5, 180], "weight": 1}, {"vertices": [5, 217, 225], "weight": 1}, {"vertices": [5, 228, 271], "weight": 1}, {"vertices": [5, 329, 332], "weight": 1}, {"vertices": [5, 333, 334], "weight": 1}, {"vertices": [5, 337, 338], "weight": 1}, {"vertices": [6, 18, 50], "weight": 1}, {"vertices": [6, 53, 61], "weight": 1}, {"vertices": [6, 63, 71], "weight": 1}, {"vertices": [6, 73, 74], "weight": 1}, {"vertices": [6, 78], "weight": 1}, {"vertices": [6, 94, 103], "weight": 1}, {"vertices": [6, 109], "weight": 1}, {"vertices": [6, 115, 119, 122], "weight": 1}, {"vertices": [6, 123, 124], "weight": 1}, {"vertices": [6, 128, 129, 131], "weight": 1}, {"vertices": [6, 141], "weight": 1}, {"vertices": [6, 145, 154], "weight": 1}, {"vertices": [6, 159, 172], "weight": 1}, {"vertices": [6, 174, 177], "weight": 1}, {"vertices": [6, 179], "weight": 1}, {"vertices": [6, 218, 226], "weight": 1}, {"vertices": [6, 247], "weight": 1}, {"vertices": [6, 250], "weight": 1}, {"vertices": [6, 256, 322], "weight": 1}, {"vertices": [7, 60], "weight": 1}, {"vertices": [7, 61, 73], "weight": 1}, {"vertices": [7, 75, 91, 95], "weight": 1}, {"vertices": [7, 96, 101], "weight": 1}, {"vertices": [7, 106, 110], "weight": 1}, {"vertices": [7, 116], "weight": 1}, {"vertices": [7, 119, 129], "weight": 1}, {"vertices": [7, 135], "weight": 1}, {"vertices": [7, 142, 144], "weight": 1}, {"vertices": [7, 147, 152], "weight": 1}, {"vertices": [7, 157, 160], "weight": 1}, {"vertices": [7, 170], "weight": 1}, {"vertices": [7, 172, 179], "weight": 1}, {"vertices": [7, 181, 189], "weight": 1}, {"vertices": [7, 208, 219], "weight": 1}, {"vertices": [7, 239], "weight": 1}, {"vertices": [7, 240], "weight": 1}, {"vertices": [7, 242, 269], "weight": 1}, {"vertices": [7, 273], "weight": 1}, {"vertices": [7, 276, 277, 278], "weight": 1}, {"vertices": [7, 279, 280], "weight": 1}, {"vertices": [7, 284, 285, 286], "weight": 1}, {"vertices": [7, 289], "weight": 1}, {"vertices": [7, 292, 321], "weight": 1}, {"vertices": [7, 324, 326], "weight": 1}, {"vertices": [7, 329, 338], "weight": 1}, {"vertices": [7, 341], "weight": 1}, {"vertices": [8, 43, 51, 52], "weight": 1}, {"vertices": [8, 54, 81], "weight": 1}, {"vertices": [8, 82, 85, 87], "weight": 1}, {"vertices": [8, 93], "weight": 1}, {"vertices": [8, 95, 106], "weight": 1}, {"vertices": [8, 111], "weight": 1}, {"vertices": [8, 140], "weight": 1}, {"vertices": [8, 144, 157], "weight": 1}, {"vertices": [8, 161, 164, 165], "weight": 1}, {"vertices": [8, 166, 192], "weight": 1}, {"vertices": [8, 194, 195], "weight": 1}, {"vertices": [8, 198], "weight": 1}, {"vertices": [8, 200, 209], "weight": 1}, {"vertices": [8, 238], "weight": 1}, {"vertices": [8, 249], "weight": 1}, {"vertices": [8, 251, 259], "weight": 1}, {"vertices": [8, 261, 262], "weight": 1}, {"vertices": [8, 277, 285], "weight": 1}, {"vertices": [8, 290], "weight": 1}, {"vertices": [8, 294, 303], "weight": 1}, {"vertices": [8, 305, 307], "weight": 1}, {"vertices": [8, 310, 313], "weight": 1}, {"vertices": [8, 319, 331], "weight": 1}, {"vertices": [8, 332, 337], "weight": 1}, {"vertices": [8, 340, 342], "weight": 1}, {"vertices": [9, 27], "weight": 1}, {"vertices": [9, 30, 38], "weight": 1}, {"vertices": [9, 44], "weight": 1}, {"vertices": [9, 59], "weight": 1}, {"vertices": [9, 60, 75], "weight": 1}, {"vertices": [9, 76], "weight": 1}, {"vertices": [9, 93, 111], "weight": 1}, {"vertices": [9, 117, 120], "weight": 1}, {"vertices": [9, 122, 128], "weight": 1}, {"vertices": [9, 133, 136], "weight": 1}, {"vertices": [9, 140, 161], "weight": 1}, {"vertices": [9, 173], "weight": 1}, {"vertices": [9, 175, 180], "weight": 1}, {"vertices": [9, 182], "weight": 1}, {"vertices": [9, 201, 210], "weight": 1}, {"vertices": [9, 248], "weight": 1}, {"vertices": [9, 249, 261], "weight": 1}, {"vertices": [9, 263], "weight": 1}, {"vertices": [9, 270, 272], "weight": 1}, {"vertices": [9, 278, 284], "weight": 1}, {"vertices": [9, 287, 288], "weight": 1}, {"vertices": [9, 299, 300], "weight": 1}, {"vertices": [9, 302, 311], "weight": 1}, {"vertices": [9, 315, 316], "weight": 1}, {"vertices": [9, 330], "weight": 1}, {"vertices": [9, 331, 340], "weight": 1}, {"vertices": [9, 343], "weight": 1}, {"vertices": [10, 28], "weight": 1}, {"vertices": [10, 29, 36], "weight": 1}, {"vertices": [10, 39], "weight": 1}, {"vertices": [10, 43, 87], "weight": 1}, {"vertices": [10, 91, 110], "weight": 1}, {"vertices": [10, 112], "weight": 1}, {"vertices": [10, 120, 133], "weight": 1}, {"vertices": [10, 138], "weight": 1}, {"vertices": [10, 142, 160], "weight": 1}, {"vertices": [10, 164, 195, 199], "weight": 1}, {"vertices": [10, 211, 220], "weight": 1}, {"vertices": [10, 236, 266], "weight": 1}, {"vertices": [10, 272, 287], "weight": 1}, {"vertices": [10, 291], "weight": 1}, {"vertices": [10, 301], "weight": 1}, {"vertices": [10, 303, 310], "weight": 1}, {"vertices": [10, 312], "weight": 1}, {"vertices": [11, 25], "weight": 1}, {"vertices": [11, 28, 39], "weight": 1}, {"vertices": [11, 42, 57], "weight": 1}, {"vertices": [11, 59, 76], "weight": 1}, {"vertices": [11, 77], "weight": 1}, {"vertices": [11, 78, 109], "weight": 1}, {"vertices": [11, 112, 138], "weight": 1}, {"vertices": [11, 141, 159], "weight": 1}, {"vertices": [11, 162, 171], "weight": 1}, {"vertices": [11, 173, 182], "weight": 1}, {"vertices": [11, 184, 185], "weight": 1}, {"vertices": [11, 221, 227, 240, 273, 289, 324], "weight": 1}, {"vertices": [11, 330, 343], "weight": 1}, {"vertices": [12, 26], "weight": 1}, {"vertices": [12, 27, 44], "weight": 1}, {"vertices": [12, 45], "weight": 1}, {"vertices": [12, 168], "weight": 1}, {"vertices": [12, 170, 181], "weight": 1}, {"vertices": [12, 183], "weight": 1}, {"vertices": [12, 190, 193, 197], "weight": 1}, {"vertices": [12, 212, 222], "weight": 1}, {"vertices": [12, 234, 235, 237, 245], "weight": 1}, {"vertices": [12, 247, 250], "weight": 1}, {"vertices": [12, 265, 266, 291], "weight": 1}, {"vertices": [12, 295, 296], "weight": 1}, {"vertices": [12, 297, 320], "weight": 1}, {"vertices": [12, 323, 325], "weight": 1}, {"vertices": [13, 19], "weight": 1}, {"vertices": [13, 21, 49, 51, 85], "weight": 1}, {"vertices": [13, 89], "weight": 1}, {"vertices": [13, 92, 105, 117, 136, 137, 156], "weight": 1}, {"vertices": [13, 169], "weight": 1}, {"vertices": [13, 171, 184], "weight": 1}, {"vertices": [13, 187], "weight": 1}, {"vertices": [13, 190], "weight": 1}, {"vertices": [13, 202, 213, 223, 229], "weight": 1}, {"vertices": [13, 237, 243, 268], "weight": 1}, {"vertices": [13, 295, 325], "weight": 1}, {"vertices": [14, 24], "weight": 1}, {"vertices": [14, 25, 42], "weight": 1}, {"vertices": [14, 46, 55], "weight": 1}, {"vertices": [14, 56, 65], "weight": 1}, {"vertices": [14, 79, 80, 108, 116, 135], "weight": 1}, {"vertices": [14, 139, 158, 167], "weight": 1}, {"vertices": [14, 168, 183], "weight": 1}, {"vertices": [14, 191], "weight": 1}, {"vertices": [14, 193], "weight": 1}, {"vertices": [14, 203, 230], "weight": 1}, {"vertices": [14, 235], "weight": 1}, {"vertices": [14, 244], "weight": 1}, {"vertices": [14, 245, 246], "weight": 1}, {"vertices": [14, 248, 263], "weight": 1}, {"vertices": [14, 264, 265], "weight": 1}, {"vertices": [14, 267], "weight": 1}, {"vertices": [14, 270, 288], "weight": 1}, {"vertices": [14, 293], "weight": 1}, {"vertices": [14, 300, 315], "weight": 1}, {"vertices": [14, 317], "weight": 1}, {"vertices": [14, 319, 342], "weight": 1}, {"vertices": [15, 19, 89], "weight": 1}, {"vertices": [15, 166], "weight": 1}, {"vertices": [15, 167], "weight": 1}, {"vertices": [15, 169, 187], "weight": 1}, {"vertices": [15, 191], "weight": 1}, {"vertices": [15, 192], "weight": 1}, {"vertices": [15, 204, 214, 262, 290, 293, 317], "weight": 1}, {"vertices": [16, 23], "weight": 1}, {"vertices": [16, 24], "weight": 1}, {"vertices": [16, 26, 45], "weight": 1}, {"vertices": [16, 46], "weight": 1}, {"vertices": [16, 47, 54], "weight": 1}, {"vertices": [16, 55], "weight": 1}, {"vertices": [16, 57, 77], "weight": 1}, {"vertices": [16, 79], "weight": 1}, {"vertices": [16, 81], "weight": 1}, {"vertices": [16, 84, 104, 115, 131], "weight": 1}, {"vertices": [16, 163], "weight": 1}, {"vertices": [16, 165, 194], "weight": 1}, {"vertices": [16, 196, 197], "weight": 1}, {"vertices": [16, 215, 231], "weight": 1}, {"vertices": [16, 234], "weight": 1}, {"vertices": [16, 298], "weight": 1}, {"vertices": [16, 299], "weight": 1}, {"vertices": [16, 301, 312], "weight": 1}, {"vertices": [16, 316], "weight": 1}, {"vertices": [16, 318], "weight": 1}, {"vertices": [17, 22, 48, 52, 82, 83, 107], "weight": 1}, {"vertices": [17, 114, 132, 134, 155], "weight": 1}, {"vertices": [17, 163, 196, 216, 224, 246, 264, 276, 286, 296, 323, 326, 341], "weight": 1}], "circuit": {"bits": [], "commands": [{"args": [["q", [2]]], "op": {"params": ["1.5"], "type": "Rz"}}, {"args": [["q", [5]]], "op": {"type": "H"}}, {"args": [["q", [6]]], "op": {"type": "H"}}, {"args": [["q", [9]]], "op": {"type": "H"}}, {"args": [["q", [14]]], "op": {"type": "H"}}, {"args": [["q", [15]]], "op": {"type": "H"}}, {"args": [["q", [16]]], "op": {"type": "H"}}, {"args": [["q", [17]]], "op": {"type": "H"}}, {"args": [["q", [2]]], "op": {"type": "H"}}, {"args": [["q", [5]]], "op": {"params": ["-3.5"], "type": "Rz"}}, {"args": [["q", [6]]], "op": {"params": ["-1.5"], "type": "Rz"}}, {"args": [["q", [9]]], "op": {"params": ["-1.5"], "type": "Rz"}}, {"args": [["q", [14]]], "op": {"params": ["-1.5"], "type": "Rz"}}, {"args": [["q", [15]]], "op": {"params": ["1"], "type": "Rz"}}, {"args": [["q", [16]]], "op": {"params": ["-1.0"], "type": "Rz"}}, {"args": [["q", [17]]], "op": {"params": ["2.5"], "type": "Rz"}}, {"args": [["q", [6]], ["q", [1]]], "op": {"params": ["1.0"], "type": "CU1"}}, {"args": [["q", [2]]], "op": {"params": ["1.5"], "type": "Rz"}}, {"args": [["q", [15]], ["q", [13]]], "op": {"params": ["1.0"], "type": "CU1"}}, {"args": [["q", [16]]], "op": {"type": "H"}}, {"args": [["q", [5]], ["q", [2]]], "op": {"params": ["1.0"], "type": "CU1"}}, {"args": [["q", [13]]], "op": {"type": "H"}}, {"args": [["q", [13]], ["q", [1]]], "op": {"params": ["1.0"], "type": "CU1"}}, {"args": [["q", [17]], ["q", [1]]], "op": {"params": ["1.0"], "type": "CU1"}}, {"args": [["q", [1]]], "op": {"type": "H"}}, {"args": [["q", [1]], ["q", [16]]], "op": {"params": ["1.0"], "type": "CU1"}}, {"args": [["q", [16]]], "op": {"type": "H"}}, {"args": [["q", [16]]], "op": {"params": ["-1/2"], "type": "Rz"}}, {"args": [["q", [16]], ["q", [14]]], "op": {"params": ["1.0"], "type": "CU1"}}, {"args": [["q", [14]]], "op": {"type": "H"}}, {"args": [["q", [16]]], "op": {"type": "H"}}, {"args": [["q", [14]], ["q", [11]]], "op": {"params": ["1.0"], "type": "CU1"}}, {"args": [["q", [16]], ["q", [12]]], "op": {"params": ["1.0"], "type": "CU1"}}, {"args": [["q", [11]]], "op": {"type": "H"}}, {"args": [["q", [12]]], "op": {"type": "H"}}, {"args": [["q", [12]], ["q", [9]]], "op": {"params": ["1.0"], "type": "CU1"}}, {"args": [["q", [11]], ["q", [10]]], "op": {"params": ["1.0"], "type": "CU1"}}, {"args": [["q", [9]]], "op": {"type": "H"}}, {"args": [["q", [10]]], "op": {"type": "H"}}, {"args": [["q", [10]], ["q", [3]]], "op": {"params": ["1.0"], "type": "CU1"}}, {"args": [["q", [9]], ["q", [5]]], "op": {"params": ["1.0"], "type": "CU1"}}, {"args": [["q", [3]]], "op": {"type": "H"}}, {"args": [["q", [5]]], "op": {"type": "H"}}, {"args": [["q", [3]], ["q", [2]]], "op": {"params": ["1.0"], "type": "CU1"}}, {"args": [["q", [5]], ["q", [4]]], "op": {"params": ["1.0"], "type": "CU1"}}, {"args": [["q", [2]]], "op": {"type": "H"}}, {"args": [["q", [4]]], "op": {"type": "H"}}, {"args": [["q", [4]], ["q", [0]]], "op": {"params": ["1.0"], "type": "CU1"}}, {"args": [["q", [2]]], "op": {"params": ["0.920870401318936"], "type": "Rz"}}, {"args": [["q", [0]]], "op": {"type": "H"}}, {"args": [["q", [2]]], "op": {"type": "H"}}, {"args": [["q", [0]]], "op": {"params": ["0.937063384102447"], "type": "Rz"}}, {"args": [["q", [2]]], "op": {"params": ["2.5"], "type": "Rz"}}, {"args": [["q", [0]]], "op": {"type": "H"}}, {"args": [["q", [3]], ["q", [2]]], "op": {"params": ["1.0"], "type": "CU1"}}, {"args": [["q", [4]], ["q", [0]]], "op": {"params": ["1.0"], "type": "CU1"}}, {"args": [["q", [3]]], "op": {"type": "H"}}, {"args": [["q", [0]]], "op": {"type": "H"}}, {"args": [["q", [3]]], "op": {"params": ["-0.5"], "type": "Rz"}}, {"args": [["q", [4]]], "op": {"type": "H"}}, {"args": [["q", [0]]], "op": {"params": ["0.5"], "type": "Rz"}}, {"args": [["q", [10]], ["q", [3]]], "op": {"params": ["1.0"], "type": "CU1"}}, {"args": [["q", [5]], ["q", [4]]], "op": {"params": ["1.0"], "type": "CU1"}}, {"args": [["q", [3]]], "op": {"type": "H"}}, {"args": [["q", [4]]], "op": {"type": "H"}}, {"args": [["q", [5]]], "op": {"type": "H"}}, {"args": [["q", [10]]], "op": {"type": "H"}}, {"args": [["q", [3]]], "op": {"params": ["-2.5"], "type": "Rz"}}, {"args": [["q", [4]]], "op": {"params": ["-1.5"], "type": "Rz"}}, {"args": [["q", [9]], ["q", [5]]], "op": {"params": ["1.0"], "type": "CU1"}}, {"args": [["q", [11]], ["q", [10]]], "op": {"params": ["1.0"], "type": "CU1"}}, {"args": [["q", [5]], ["q", [2]]], "op": {"params": ["1.0"], "type": "CU1"}}, {"args": [["q", [4]], ["q", [3]]], "op": {"params": ["1.0"], "type": "CU1"}}, {"args": [["q", [9]]], "op": {"type": "H"}}, {"args": [["q", [10]]], "op": {"type": "H"}}, {"args": [["q", [11]]], "op": {"type": "H"}}, {"args": [["q", [2]]], "op": {"type": "H"}}, {"args": [["q", [9]]], "op": {"params": ["-0.5"], "type": "Rz"}}, {"args": [["q", [10]]], "op": {"params": ["0.5"], "type": "Rz"}}, {"args": [["q", [14]], ["q", [11]]], "op": {"params": ["1.0"], "type": "CU1"}}, {"args": [["q", [2]]], "op": {"params": ["0.5"], "type": "Rz"}}, {"args": [["q", [10]], ["q", [8]]], "op": {"params": ["1.0"], "type": "CU1"}}, {"args": [["q", [12]], ["q", [9]]], "op": {"params": ["1.0"], "type": "CU1"}}, {"args": [["q", [14]]], "op": {"type": "H"}}, {"args": [["q", [9]]], "op": {"type": "H"}}, {"args": [["q", [12]]], "op": {"type": "H"}}, {"args": [["q", [16]], ["q", [12]]], "op": {"params": ["1.0"], "type": "CU1"}}, {"args": [["q", [12]]], "op": {"type": "H"}}, {"args": [["q", [16]]], "op": {"type": "H"}}, {"args": [["q", [12]]], "op": {"params": ["0.5"], "type": "Rz"}}, {"args": [["q", [16]]], "op": {"params": ["1/2"], "type": "Rz"}}, {"args": [["q", [16]], ["q", [14]]], "op": {"params": ["1.0"], "type": "CU1"}}, {"args": [["q", [16]]], "op": {"type": "H"}}, {"args": [["q", [1]], ["q", [16]]], "op": {"params": ["1.0"], "type": "CU1"}}, {"args": [["q", [1]]], "op": {"type": "H"}}, {"args": [["q", [17]], ["q", [1]]], "op": {"params": ["1.0"], "type": "CU1"}}, {"args": [["q", [13]], ["q", [1]]], "op": {"params": ["1.0"], "type": "CU1"}}, {"args": [["q", [6]], ["q", [1]]], "op": {"params": ["1.0"], "type": "CU1"}}, {"args": [["q", [13]], ["q", [8]]], "op": {"params": ["1.0"], "type": "CU1"}}, {"args": [["q", [6]]], "op": {"type": "H"}}, {"args": [["q", [17]], ["q", [8]]], "op": {"params": ["1.0"], "type": "CU1"}}, {"args": [["q", [6]], ["q", [5]]], "op": {"params": ["1.0"], "type": "CU1"}}, {"args": [["q", [8]]], "op": {"type": "H"}}, {"args": [["q", [8]], ["q", [16]]], "op": {"params": ["1.0"], "type": "CU1"}}, {"args": [["q", [16]]], "op": {"type": "H"}}, {"args": [["q", [16]]], "op": {"params": ["-1/2"], "type": "Rz"}}, {"args": [["q", [16]], ["q", [14]]], "op": {"params": ["1.0"], "type": "CU1"}}, {"args": [["q", [14]]], "op": {"type": "H"}}, {"args": [["q", [16]]], "op": {"type": "H"}}, {"args": [["q", [14]], ["q", [5]]], "op": {"params": ["1.0"], "type": "CU1"}}, {"args": [["q", [16]], ["q", [11]]], "op": {"params": ["1.0"], "type": "CU1"}}, {"args": [["q", [5]]], "op": {"type": "H"}}, {"args": [["q", [11]]], "op": {"type": "H"}}, {"args": [["q", [5]], ["q", [3]]], "op": {"params": ["1.0"], "type": "CU1"}}, {"args": [["q", [11]], ["q", [9]]], "op": {"params": ["1.0"], "type": "CU1"}}, {"args": [["q", [3]]], "op": {"type": "H"}}, {"args": [["q", [9]]], "op": {"type": "H"}}, {"args": [["q", [3]]], "op": {"params": ["-0.897032197321521"], "type": "Rz"}}, {"args": [["q", [9]], ["q", [7]]], "op": {"params": ["1.0"], "type": "CU1"}}, {"args": [["q", [3]]], "op": {"type": "H"}}, {"args": [["q", [7]]], "op": {"type": "H"}}, {"args": [["q", [3]]], "op": {"params": ["2.5"], "type": "Rz"}}, {"args": [["q", [7]], ["q", [6]]], "op": {"params": ["1.0"], "type": "CU1"}}, {"args": [["q", [5]], ["q", [3]]], "op": {"params": ["1.0"], "type": "CU1"}}, {"args": [["q", [6]]], "op": {"type": "H"}}, {"args": [["q", [6]], ["q", [4]]], "op": {"params": ["1.0"], "type": "CU1"}}, {"args": [["q", [5]]], "op": {"type": "H"}}, {"args": [["q", [4]]], "op": {"type": "H"}}, {"args": [["q", [5]]], "op": {"params": ["1.5"], "type": "Rz"}}, {"args": [["q", [4]], ["q", [2]]], "op": {"params": ["1.0"], "type": "CU1"}}, {"args": [["q", [14]], ["q", [5]]], "op": {"params": ["1.0"], "type": "CU1"}}, {"args": [["q", [2]]], "op": {"type": "H"}}, {"args": [["q", [14]]], "op": {"type": "H"}}, {"args": [["q", [2]], ["q", [1]]], "op": {"params": ["1.0"], "type": "CU1"}}, {"args": [["q", [1]]], "op": {"type": "H"}}, {"args": [["q", [1]], ["q", [0]]], "op": {"params": ["1.0"], "type": "CU1"}}, {"args": [["q", [0]]], "op": {"type": "H"}}, {"args": [["q", [0]]], "op": {"params": ["-1.79735755934783"], "type": "Rz"}}, {"args": [["q", [0]]], "op": {"type": "H"}}, {"args": [["q", [0]]], "op": {"params": ["-0.5"], "type": "Rz"}}, {"args": [["q", [1]], ["q", [0]]], "op": {"params": ["1.0"], "type": "CU1"}}, {"args": [["q", [0]]], "op": {"type": "H"}}, {"args": [["q", [1]]], "op": {"type": "H"}}, {"args": [["q", [2]], ["q", [1]]], "op": {"params": ["1.0"], "type": "CU1"}}, {"args": [["q", [1]]], "op": {"type": "H"}}, {"args": [["q", [2]]], "op": {"type": "H"}}, {"args": [["q", [1]]], "op": {"params": ["0.5"], "type": "Rz"}}, {"args": [["q", [4]], ["q", [2]]], "op": {"params": ["1.0"], "type": "CU1"}}, {"args": [["q", [4]]], "op": {"type": "H"}}, {"args": [["q", [4]]], "op": {"params": ["3.5"], "type": "Rz"}}, {"args": [["q", [6]], ["q", [4]]], "op": {"params": ["1.0"], "type": "CU1"}}, {"args": [["q", [4]], ["q", [3]]], "op": {"params": ["1.0"], "type": "CU1"}}, {"args": [["q", [6]]], "op": {"type": "H"}}, {"args": [["q", [3]]], "op": {"type": "H"}}, {"args": [["q", [4]]], "op": {"type": "H"}}, {"args": [["q", [6]]], "op": {"params": ["2.5"], "type": "Rz"}}, {"args": [["q", [3]]], "op": {"params": ["-1.5"], "type": "Rz"}}, {"args": [["q", [7]], ["q", [6]]], "op": {"params": ["1.0"], "type": "CU1"}}, {"args": [["q", [6]], ["q", [5]]], "op": {"params": ["1.0"], "type": "CU1"}}, {"args": [["q", [7]]], "op": {"type": "H"}}, {"args": [["q", [5]]], "op": {"type": "H"}}, {"args": [["q", [6]]], "op": {"type": "H"}}, {"args": [["q", [9]], ["q", [7]]], "op": {"params": ["1.0"], "type": "CU1"}}, {"args": [["q", [6]]], "op": {"params": ["0.5"], "type": "Rz"}}, {"args": [["q", [9]]], "op": {"type": "H"}}, {"args": [["q", [11]], ["q", [9]]], "op": {"params": ["1.0"], "type": "CU1"}}, {"args": [["q", [9]]], "op": {"type": "H"}}, {"args": [["q", [11]]], "op": {"type": "H"}}, {"args": [["q", [16]], ["q", [11]]], "op": {"params": ["1.0"], "type": "CU1"}}, {"args": [["q", [11]]], "op": {"type": "H"}}, {"args": [["q", [16]]], "op": {"type": "H"}}, {"args": [["q", [11]]], "op": {"params": ["0.5"], "type": "Rz"}}, {"args": [["q", [16]]], "op": {"params": ["1/2"], "type": "Rz"}}, {"args": [["q", [11]], ["q", [6]]], "op": {"params": ["1.0"], "type": "CU1"}}, {"args": [["q", [16]], ["q", [14]]], "op": {"params": ["1.0"], "type": "CU1"}}, {"args": [["q", [14]], ["q", [4]]], "op": {"params": ["1.0"], "type": "CU1"}}, {"args": [["q", [6]]], "op": {"type": "H"}}, {"args": [["q", [16]]], "op": {"type": "H"}}, {"args": [["q", [4]]], "op": {"type": "H"}}, {"args": [["q", [8]], ["q", [16]]], "op": {"params": ["1.0"], "type": "CU1"}}, {"args": [["q", [8]]], "op": {"type": "H"}}, {"args": [["q", [16]]], "op": {"type": "H"}}, {"args": [["q", [17]], ["q", [8]]], "op": {"params": ["1.0"], "type": "CU1"}}, {"args": [["q", [16]]], "op": {"params": ["-1.0"], "type": "Rz"}}, {"args": [["q", [17]], ["q", [2]]], "op": {"params": ["1.0"], "type": "CU1"}}, {"args": [["q", [16]], ["q", [3]]], "op": {"params": ["1.0"], "type": "CU1"}}, {"args": [["q", [13]], ["q", [8]]], "op": {"params": ["1.0"], "type": "CU1"}}, {"args": [["q", [2]]], "op": {"type": "H"}}, {"args": [["q", [4]], ["q", [3]]], "op": {"params": ["1.0"], "type": "CU1"}}, {"args": [["q", [10]], ["q", [8]]], "op": {"params": ["1.0"], "type": "CU1"}}, {"args": [["q", [13]]], "op": {"type": "H"}}, {"args": [["q", [2]], ["q", [1]]], "op": {"params": ["1.0"], "type": "CU1"}}, {"args": [["q", [3]]], "op": {"type": "H"}}, {"args": [["q", [8]]], "op": {"type": "H"}}, {"args": [["q", [10]]], "op": {"type": "H"}}, {"args": [["q", [15]], ["q", [13]]], "op": {"params": ["1.0"], "type": "CU1"}}, {"args": [["q", [3]], ["q", [1]]], "op": {"params": ["1.0"], "type": "CU1"}}, {"args": [["q", [10]], ["q", [7]]], "op": {"params": ["1.0"], "type": "CU1"}}, {"args": [["q", [8]]], "op": {"params": ["0.5"], "type": "Rz"}}, {"args": [["q", [13]]], "op": {"type": "H"}}, {"args": [["q", [15]]], "op": {"type": "H"}}, {"args": [["q", [13]], ["q", [5]]], "op": {"params": ["1.0"], "type": "CU1"}}, {"args": [["q", [9]], ["q", [8]]], "op": {"params": ["1.0"], "type": "CU1"}}, {"args": [["q", [6]], ["q", [5]]], "op": {"params": ["1.0"], "type": "CU1"}}, {"args": [["q", [8]]], "op": {"type": "H"}}, {"args": [["q", [8]], ["q", [7]]], "op": {"params": ["1.0"], "type": "CU1"}}, {"args": [["q", [7]]], "op": {"type": "H"}}, {"args": [["q", [7]], ["q", [5]]], "op": {"params": ["1.0"], "type": "CU1"}}, {"args": [["q", [5]]], "op": {"type": "H"}}, {"args": [["q", [5]], ["q", [1]]], "op": {"params": ["1.0"], "type": "CU1"}}, {"args": [["q", [1]]], "op": {"type": "H"}}, {"args": [["q", [1]]], "op": {"params": ["1.8369037307553"], "type": "Rz"}}, {"args": [["q", [1]]], "op": {"type": "H"}}, {"args": [["q", [1]]], "op": {"params": ["3.5"], "type": "Rz"}}, {"args": [["q", [5]], ["q", [1]]], "op": {"params": ["1.0"], "type": "CU1"}}, {"args": [["q", [3]], ["q", [1]]], "op": {"params": ["1.0"], "type": "CU1"}}, {"args": [["q", [5]]], "op": {"type": "H"}}, {"args": [["q", [2]], ["q", [1]]], "op": {"params": ["1.0"], "type": "CU1"}}, {"args": [["q", [3]]], "op": {"type": "H"}}, {"args": [["q", [7]], ["q", [5]]], "op": {"params": ["1.0"], "type": "CU1"}}, {"args": [["q", [1]]], "op": {"type": "H"}}, {"args": [["q", [2]]], "op": {"type": "H"}}, {"args": [["q", [4]], ["q", [3]]], "op": {"params": ["1.0"], "type": "CU1"}}, {"args": [["q", [6]], ["q", [5]]], "op": {"params": ["1.0"], "type": "CU1"}}, {"args": [["q", [7]]], "op": {"type": "H"}}, {"args": [["q", [2]]], "op": {"params": ["1.5"], "type": "Rz"}}, {"args": [["q", [16]], ["q", [3]]], "op": {"params": ["1.0"], "type": "CU1"}}, {"args": [["q", [4]]], "op": {"type": "H"}}, {"args": [["q", [13]], ["q", [5]]], "op": {"params": ["1.0"], "type": "CU1"}}, {"args": [["q", [6]]], "op": {"type": "H"}}, {"args": [["q", [8]], ["q", [7]]], "op": {"params": ["1.0"], "type": "CU1"}}, {"args": [["q", [17]], ["q", [2]]], "op": {"params": ["1.0"], "type": "CU1"}}, {"args": [["q", [3]]], "op": {"type": "H"}}, {"args": [["q", [14]], ["q", [4]]], "op": {"params": ["1.0"], "type": "CU1"}}, {"args": [["q", [11]], ["q", [6]]], "op": {"params": ["1.0"], "type": "CU1"}}, {"args": [["q", [10]], ["q", [7]]], "op": {"params": ["1.0"], "type": "CU1"}}, {"args": [["q", [8]]], "op": {"type": "H"}}, {"args": [["q", [2]]], "op": {"type": "H"}}, {"args": [["q", [3]]], "op": {"params": ["0.5"], "type": "Rz"}}, {"args": [["q", [4]]], "op": {"type": "H"}}, {"args": [["q", [6]]], "op": {"type": "H"}}, {"args": [["q", [7]]], "op": {"type": "H"}}, {"args": [["q", [8]]], "op": {"params": ["-0.5"], "type": "Rz"}}, {"args": [["q", [10]]], "op": {"type": "H"}}, {"args": [["q", [11]]], "op": {"type": "H"}}, {"args": [["q", [17]]], "op": {"type": "H"}}, {"args": [["q", [2]]], "op": {"params": ["-0.5"], "type": "Rz"}}, {"args": [["q", [4]]], "op": {"params": ["0.5"], "type": "Rz"}}, {"args": [["q", [6]]], "op": {"params": ["0.5"], "type": "Rz"}}, {"args": [["q", [7]]], "op": {"params": ["0.5"], "type": "Rz"}}, {"args": [["q", [9]], ["q", [8]]], "op": {"params": ["1.0"], "type": "CU1"}}, {"args": [["q", [11]], ["q", [10]]], "op": {"params": ["1.0"], "type": "CU1"}}, {"args": [["q", [2]], ["q", [0]]], "op": {"params": ["1.0"], "type": "CU1"}}, {"args": [["q", [17]], ["q", [4]]], "op": {"params": ["1.0"], "type": "CU1"}}, {"args": [["q", [16]], ["q", [6]]], "op": {"params": ["1.0"], "type": "CU1"}}, {"args": [["q", [14]], ["q", [7]]], "op": {"params": ["1.0"], "type": "CU1"}}, {"args": [["q", [8]]], "op": {"type": "H"}}, {"args": [["q", [9]]], "op": {"type": "H"}}, {"args": [["q", [10]]], "op": {"type": "H"}}, {"args": [["q", [4]]], "op": {"type": "H"}}, {"args": [["q", [7]]], "op": {"type": "H"}}, {"args": [["q", [13]], ["q", [9]]], "op": {"params": ["1.0"], "type": "CU1"}}, {"args": [["q", [4]], ["q", [3]]], "op": {"params": ["1.0"], "type": "CU1"}}, {"args": [["q", [7]], ["q", [6]]], "op": {"params": ["1.0"], "type": "CU1"}}, {"args": [["q", [10]], ["q", [9]]], "op": {"params": ["1.0"], "type": "CU1"}}, {"args": [["q", [3]]], "op": {"type": "H"}}, {"args": [["q", [9]]], "op": {"type": "H"}}, {"args": [["q", [3]], ["q", [0]]], "op": {"params": ["1.0"], "type": "CU1"}}, {"args": [["q", [9]], ["q", [6]]], "op": {"params": ["1.0"], "type": "CU1"}}, {"args": [["q", [6]]], "op": {"type": "H"}}, {"args": [["q", [6]], ["q", [0]]], "op": {"params": ["1.0"], "type": "CU1"}}, {"args": [["q", [0]]], "op": {"type": "H"}}, {"args": [["q", [0]]], "op": {"params": ["0.363297927418039"], "type": "Rz"}}, {"args": [["q", [0]]], "op": {"type": "H"}}, {"args": [["q", [6]], ["q", [0]]], "op": {"params": ["1.0"], "type": "CU1"}}, {"args": [["q", [3]], ["q", [0]]], "op": {"params": ["1.0"], "type": "CU1"}}, {"args": [["q", [6]]], "op": {"type": "H"}}, {"args": [["q", [2]], ["q", [0]]], "op": {"params": ["1.0"], "type": "CU1"}}, {"args": [["q", [3]]], "op": {"type": "H"}}, {"args": [["q", [6]]], "op": {"params": ["3.5"], "type": "Rz"}}, {"args": [["q", [2]]], "op": {"type": "H"}}, {"args": [["q", [4]], ["q", [3]]], "op": {"params": ["1.0"], "type": "CU1"}}, {"args": [["q", [9]], ["q", [6]]], "op": {"params": ["1.0"], "type": "CU1"}}, {"args": [["q", [2]]], "op": {"params": ["1.5"], "type": "Rz"}}, {"args": [["q", [4]]], "op": {"type": "H"}}, {"args": [["q", [7]], ["q", [6]]], "op": {"params": ["1.0"], "type": "CU1"}}, {"args": [["q", [9]]], "op": {"type": "H"}}, {"args": [["q", [2]], ["q", [0]]], "op": {"params": ["1.0"], "type": "CU1"}}, {"args": [["q", [4]]], "op": {"params": ["-0.5"], "type": "Rz"}}, {"args": [["q", [16]], ["q", [6]]], "op": {"params": ["1.0"], "type": "CU1"}}, {"args": [["q", [7]]], "op": {"type": "H"}}, {"args": [["q", [9]]], "op": {"params": ["3.5"], "type": "Rz"}}, {"args": [["q", [17]], ["q", [4]]], "op": {"params": ["1.0"], "type": "CU1"}}, {"args": [["q", [6]]], "op": {"type": "H"}}, {"args": [["q", [7]]], "op": {"params": ["-0.5"], "type": "Rz"}}, {"args": [["q", [10]], ["q", [9]]], "op": {"params": ["1.0"], "type": "CU1"}}, {"args": [["q", [16]]], "op": {"type": "H"}}, {"args": [["q", [17]], ["q", [3]]], "op": {"params": ["1.0"], "type": "CU1"}}, {"args": [["q", [4]]], "op": {"type": "H"}}, {"args": [["q", [14]], ["q", [7]]], "op": {"params": ["1.0"], "type": "CU1"}}, {"args": [["q", [13]], ["q", [9]]], "op": {"params": ["1.0"], "type": "CU1"}}, {"args": [["q", [10]]], "op": {"type": "H"}}, {"args": [["q", [13]], ["q", [5]]], "op": {"params": ["1.0"], "type": "CU1"}}, {"args": [["q", [7]]], "op": {"type": "H"}}, {"args": [["q", [9]]], "op": {"type": "H"}}, {"args": [["q", [11]], ["q", [10]]], "op": {"params": ["1.0"], "type": "CU1"}}, {"args": [["q", [14]]], "op": {"type": "H"}}, {"args": [["q", [14]], ["q", [4]]], "op": {"params": ["1.0"], "type": "CU1"}}, {"args": [["q", [9]], ["q", [8]]], "op": {"params": ["1.0"], "type": "CU1"}}, {"args": [["q", [10]]], "op": {"type": "H"}}, {"args": [["q", [11]]], "op": {"type": "H"}}, {"args": [["q", [4]]], "op": {"type": "H"}}, {"args": [["q", [11]], ["q", [6]]], "op": {"params": ["1.0"], "type": "CU1"}}, {"args": [["q", [10]], ["q", [7]]], "op": {"params": ["1.0"], "type": "CU1"}}, {"args": [["q", [8]]], "op": {"type": "H"}}, {"args": [["q", [4]], ["q", [3]]], "op": {"params": ["1.0"], "type": "CU1"}}, {"args": [["q", [6]]], "op": {"type": "H"}}, {"args": [["q", [8]], ["q", [7]]], "op": {"params": ["1.0"], "type": "CU1"}}, {"args": [["q", [3]]], "op": {"type": "H"}}, {"args": [["q", [6]], ["q", [5]]], "op": {"params": ["1.0"], "type": "CU1"}}, {"args": [["q", [7]]], "op": {"type": "H"}}, {"args": [["q", [3]], ["q", [0]]], "op": {"params": ["1.0"], "type": "CU1"}}, {"args": [["q", [7]], ["q", [5]]], "op": {"params": ["1.0"], "type": "CU1"}}, {"args": [["q", [5]]], "op": {"type": "H"}}, {"args": [["q", [5]], ["q", [0]]], "op": {"params": ["1.0"], "type": "CU1"}}, {"args": [["q", [0]]], "op": {"type": "H"}}, {"args": [["q", [0]]], "op": {"params": ["0.251747447931906"], "type": "Rz"}}, {"args": [["q", [0]]], "op": {"type": "H"}}, {"args": [["q", [5]], ["q", [0]]], "op": {"params": ["1.0"], "type": "CU1"}}, {"args": [["q", [3]], ["q", [0]]], "op": {"params": ["1.0"], "type": "CU1"}}, {"args": [["q", [5]]], "op": {"type": "H"}}, {"args": [["q", [2]], ["q", [0]]], "op": {"params": ["1.0"], "type": "CU1"}}, {"args": [["q", [3]]], "op": {"type": "H"}}, {"args": [["q", [7]], ["q", [5]]], "op": {"params": ["1.0"], "type": "CU1"}}, {"args": [["q", [0]]], "op": {"type": "H"}}, {"args": [["q", [4]], ["q", [3]]], "op": {"params": ["1.0"], "type": "CU1"}}, {"args": [["q", [6]], ["q", [5]]], "op": {"params": ["1.0"], "type": "CU1"}}, {"args": [["q", [7]]], "op": {"type": "H"}}, {"args": [["q", [17]], ["q", [3]]], "op": {"params": ["1.0"], "type": "CU1"}}, {"args": [["q", [4]]], "op": {"type": "H"}}, {"args": [["q", [13]], ["q", [5]]], "op": {"params": ["1.0"], "type": "CU1"}}, {"args": [["q", [6]]], "op": {"type": "H"}}, {"args": [["q", [8]], ["q", [7]]], "op": {"params": ["1.0"], "type": "CU1"}}, {"args": [["q", [3]]], "op": {"type": "H"}}, {"args": [["q", [14]], ["q", [4]]], "op": {"params": ["1.0"], "type": "CU1"}}, {"args": [["q", [11]], ["q", [6]]], "op": {"params": ["1.0"], "type": "CU1"}}, {"args": [["q", [10]], ["q", [7]]], "op": {"params": ["1.0"], "type": "CU1"}}, {"args": [["q", [8]]], "op": {"type": "H"}}, {"args": [["q", [13]]], "op": {"type": "H"}}, {"args": [["q", [17]]], "op": {"type": "H"}}, {"args": [["q", [7]]], "op": {"type": "H"}}, {"args": [["q", [9]], ["q", [8]]], "op": {"params": ["1.0"], "type": "CU1"}}, {"args": [["q", [10]]], "op": {"type": "H"}}, {"args": [["q", [11]]], "op": {"type": "H"}}, {"args": [["q", [17]]], "op": {"params": ["1.5"], "type": "Rz"}}, {"args": [["q", [11]], ["q", [3]]], "op": {"params": ["1.0"], "type": "CU1"}}, {"args": [["q", [7]]], "op": {"params": ["0.5"], "type": "Rz"}}, {"args": [["q", [9]]], "op": {"type": "H"}}, {"args": [["q", [10]]], "op": {"params": ["-0.5"], "type": "Rz"}}, {"args": [["q", [17]], ["q", [16]]], "op": {"params": ["1.0"], "type": "CU1"}}, {"args": [["q", [10]], ["q", [8]]], "op": {"params": ["1.0"], "type": "CU1"}}, {"args": [["q", [9]]], "op": {"params": ["0.5"], "type": "Rz"}}, {"args": [["q", [16]]], "op": {"type": "H"}}, {"args": [["q", [16]], ["q", [8]]], "op": {"params": ["1.0"], "type": "CU1"}}, {"args": [["q", [8]]], "op": {"type": "H"}}, {"args": [["q", [8]], ["q", [15]]], "op": {"params": ["1.0"], "type": "CU1"}}, {"args": [["q", [15]]], "op": {"type": "H"}}, {"args": [["q", [15]]], "op": {"params": ["-1/2"], "type": "Rz"}}, {"args": [["q", [15]], ["q", [14]]], "op": {"params": ["1.0"], "type": "CU1"}}, {"args": [["q", [14]]], "op": {"type": "H"}}, {"args": [["q", [15]]], "op": {"type": "H"}}, {"args": [["q", [14]], ["q", [12]]], "op": {"params": ["1.0"], "type": "CU1"}}, {"args": [["q", [15]], ["q", [13]]], "op": {"params": ["1.0"], "type": "CU1"}}, {"args": [["q", [12]]], "op": {"type": "H"}}, {"args": [["q", [13]]], "op": {"type": "H"}}, {"args": [["q", [12]], ["q", [7]]], "op": {"params": ["1.0"], "type": "CU1"}}, {"args": [["q", [13]], ["q", [11]]], "op": {"params": ["1.0"], "type": "CU1"}}, {"args": [["q", [7]]], "op": {"type": "H"}}, {"args": [["q", [11]]], "op": {"type": "H"}}, {"args": [["q", [7]], ["q", [6]]], "op": {"params": ["1.0"], "type": "CU1"}}, {"args": [["q", [11]], ["q", [9]]], "op": {"params": ["1.0"], "type": "CU1"}}, {"args": [["q", [6]]], "op": {"type": "H"}}, {"args": [["q", [9]]], "op": {"type": "H"}}, {"args": [["q", [6]], ["q", [3]]], "op": {"params": ["1.0"], "type": "CU1"}}, {"args": [["q", [9]], ["q", [5]]], "op": {"params": ["1.0"], "type": "CU1"}}, {"args": [["q", [3]]], "op": {"type": "H"}}, {"args": [["q", [5]]], "op": {"type": "H"}}, {"args": [["q", [5]], ["q", [1]]], "op": {"params": ["1.0"], "type": "CU1"}}, {"args": [["q", [3]]], "op": {"params": ["-1.39984055280777"], "type": "Rz"}}, {"args": [["q", [1]]], "op": {"type": "H"}}, {"args": [["q", [3]]], "op": {"type": "H"}}, {"args": [["q", [1]]], "op": {"params": ["-0.427666836759979"], "type": "Rz"}}, {"args": [["q", [6]], ["q", [3]]], "op": {"params": ["1.0"], "type": "CU1"}}, {"args": [["q", [1]]], "op": {"type": "H"}}, {"args": [["q", [6]]], "op": {"type": "H"}}, {"args": [["q", [5]], ["q", [1]]], "op": {"params": ["1.0"], "type": "CU1"}}, {"args": [["q", [6]]], "op": {"params": ["1.5"], "type": "Rz"}}, {"args": [["q", [5]]], "op": {"type": "H"}}, {"args": [["q", [7]], ["q", [6]]], "op": {"params": ["1.0"], "type": "CU1"}}, {"args": [["q", [5]]], "op": {"params": ["1.5"], "type": "Rz"}}, {"args": [["q", [6]]], "op": {"type": "H"}}, {"args": [["q", [7]]], "op": {"type": "H"}}, {"args": [["q", [9]], ["q", [5]]], "op": {"params": ["1.0"], "type": "CU1"}}, {"args": [["q", [12]], ["q", [7]]], "op": {"params": ["1.0"], "type": "CU1"}}, {"args": [["q", [5]]], "op": {"type": "H"}}, {"args": [["q", [9]]], "op": {"type": "H"}}, {"args": [["q", [12]]], "op": {"type": "H"}}, {"args": [["q", [5]]], "op": {"params": ["-0.5"], "type": "Rz"}}, {"args": [["q", [11]], ["q", [9]]], "op": {"params": ["1.0"], "type": "CU1"}}, {"args": [["q", [14]], ["q", [12]]], "op": {"params": ["1.0"], "type": "CU1"}}, {"args": [["q", [9]]], "op": {"type": "H"}}, {"args": [["q", [11]]], "op": {"type": "H"}}, {"args": [["q", [12]]], "op": {"type": "H"}}, {"args": [["q", [14]]], "op": {"type": "H"}}, {"args": [["q", [13]], ["q", [11]]], "op": {"params": ["1.0"], "type": "CU1"}}, {"args": [["q", [14]]], "op": {"params": ["0.5"], "type": "Rz"}}, {"args": [["q", [11]], ["q", [3]]], "op": {"params": ["1.0"], "type": "CU1"}}, {"args": [["q", [13]]], "op": {"type": "H"}}, {"args": [["q", [3]], ["q", [4]]], "op": {"params": ["1.0"], "type": "CU1"}}, {"args": [["q", [11]]], "op": {"type": "H"}}, {"args": [["q", [15]], ["q", [13]]], "op": {"params": ["1.0"], "type": "CU1"}}, {"args": [["q", [2]], ["q", [4]]], "op": {"params": ["1.0"], "type": "CU1"}}, {"args": [["q", [3]]], "op": {"type": "H"}}, {"args": [["q", [13]]], "op": {"type": "H"}}, {"args": [["q", [15]]], "op": {"type": "H"}}, {"args": [["q", [3]]], "op": {"params": ["-0.5"], "type": "Rz"}}, {"args": [["q", [13]]], "op": {"params": ["0.5"], "type": "Rz"}}, {"args": [["q", [15]]], "op": {"params": ["1/2"], "type": "Rz"}}, {"args": [["q", [3]], ["q", [7]]], "op": {"params": ["1.0"], "type": "CU1"}}, {"args": [["q", [12]], ["q", [13]]], "op": {"params": ["1.0"], "type": "CU1"}}, {"args": [["q", [15]], ["q", [14]]], "op": {"params": ["1.0"], "type": "CU1"}}, {"args": [["q", [3]]], "op": {"type": "H"}}, {"args": [["q", [7]]], "op": {"type": "H"}}, {"args": [["q", [13]]], "op": {"type": "H"}}, {"args": [["q", [14]]], "op": {"type": "H"}}, {"args": [["q", [15]]], "op": {"type": "H"}}, {"args": [["q", [3]]], "op": {"params": ["-0.5"], "type": "Rz"}}, {"args": [["q", [14]]], "op": {"params": ["0.5"], "type": "Rz"}}, {"args": [["q", [15]]], "op": {"params": ["-1.5"], "type": "Rz"}}, {"args": [["q", [8]], ["q", [15]]], "op": {"params": ["1.0"], "type": "CU1"}}, {"args": [["q", [12]], ["q", [14]]], "op": {"params": ["1.0"], "type": "CU1"}}, {"args": [["q", [8]]], "op": {"type": "H"}}, {"args": [["q", [14]]], "op": {"type": "H"}}, {"args": [["q", [15]]], "op": {"type": "H"}}, {"args": [["q", [16]], ["q", [8]]], "op": {"params": ["1.0"], "type": "CU1"}}, {"args": [["q", [15]]], "op": {"params": ["3"], "type": "Rz"}}, {"args": [["q", [10]], ["q", [8]]], "op": {"params": ["1.0"], "type": "CU1"}}, {"args": [["q", [16]]], "op": {"type": "H"}}, {"args": [["q", [8]]], "op": {"type": "H"}}, {"args": [["q", [17]], ["q", [16]]], "op": {"params": ["1.0"], "type": "CU1"}}, {"args": [["q", [8]]], "op": {"params": ["0.5"], "type": "Rz"}}, {"args": [["q", [12]], ["q", [16]]], "op": {"params": ["1.0"], "type": "CU1"}}, {"args": [["q", [3]], ["q", [8]]], "op": {"params": ["1.0"], "type": "CU1"}}, {"args": [["q", [12]]], "op": {"type": "H"}}, {"args": [["q", [16]]], "op": {"type": "H"}}, {"args": [["q", [3]], ["q", [10]]], "op": {"params": ["1.0"], "type": "CU1"}}, {"args": [["q", [8]]], "op": {"type": "H"}}, {"args": [["q", [3]]], "op": {"type": "H"}}, {"args": [["q", [8]], ["q", [4]]], "op": {"params": ["1.0"], "type": "CU1"}}, {"args": [["q", [10]]], "op": {"type": "H"}}, {"args": [["q", [9]], ["q", [4]]], "op": {"params": ["1.0"], "type": "CU1"}}, {"args": [["q", [13]], ["q", [4]]], "op": {"params": ["1.0"], "type": "CU1"}}, {"args": [["q", [14]], ["q", [4]]], "op": {"params": ["1.0"], "type": "CU1"}}, {"args": [["q", [15]], ["q", [4]]], "op": {"params": ["1.0"], "type": "CU1"}}, {"args": [["q", [4]]], "op": {"type": "H"}}, {"args": [["q", [4]]], "op": {"params": ["-0.263183528878365"], "type": "Rz"}}, {"args": [["q", [4]]], "op": {"type": "H"}}, {"args": [["q", [0]], ["q", [4]]], "op": {"params": ["1.0"], "type": "CU1"}}, {"args": [["q", [2]], ["q", [4]]], "op": {"params": ["1.0"], "type": "CU1"}}, {"args": [["q", [2]]], "op": {"type": "H"}}, {"args": [["q", [3]], ["q", [4]]], "op": {"params": ["1.0"], "type": "CU1"}}, {"args": [["q", [7]], ["q", [4]]], "op": {"params": ["1.0"], "type": "CU1"}}, {"args": [["q", [8]], ["q", [4]]], "op": {"params": ["1.0"], "type": "CU1"}}, {"args": [["q", [9]], ["q", [4]]], "op": {"params": ["1.0"], "type": "CU1"}}, {"args": [["q", [8]]], "op": {"type": "H"}}, {"args": [["q", [10]], ["q", [4]]], "op": {"params": ["1.0"], "type": "CU1"}}, {"args": [["q", [8]]], "op": {"params": ["-0.5"], "type": "Rz"}}, {"args": [["q", [9]]], "op": {"type": "H"}}, {"args": [["q", [12]], ["q", [4]]], "op": {"params": ["1.0"], "type": "CU1"}}, {"args": [["q", [13]], ["q", [4]]], "op": {"params": ["1.0"], "type": "CU1"}}, {"args": [["q", [15]], ["q", [4]]], "op": {"params": ["1.0"], "type": "CU1"}}, {"args": [["q", [16]], ["q", [4]]], "op": {"params": ["1.0"], "type": "CU1"}}, {"args": [["q", [17]], ["q", [4]]], "op": {"params": ["1.0"], "type": "CU1"}}, {"args": [["q", [4]]], "op": {"type": "H"}}, {"args": [["q", [4]]], "op": {"params": ["-0.122299931494776"], "type": "Rz"}}, {"args": [["q", [4]]], "op": {"type": "H"}}, {"args": [["q", [5]], ["q", [4]]], "op": {"params": ["1.0"], "type": "CU1"}}, {"args": [["q", [6]], ["q", [4]]], "op": {"params": ["1.0"], "type": "CU1"}}, {"args": [["q", [7]], ["q", [4]]], "op": {"params": ["1.0"], "type": "CU1"}}, {"args": [["q", [10]], ["q", [4]]], "op": {"params": ["1.0"], "type": "CU1"}}, {"args": [["q", [7]]], "op": {"type": "H"}}, {"args": [["q", [11]], ["q", [4]]], "op": {"params": ["1.0"], "type": "CU1"}}, {"args": [["q", [7]]], "op": {"params": ["-0.5"], "type": "Rz"}}, {"args": [["q", [10]]], "op": {"type": "H"}}, {"args": [["q", [12]], ["q", [4]]], "op": {"params": ["1.0"], "type": "CU1"}}, {"args": [["q", [10]]], "op": {"params": ["2.5"], "type": "Rz"}}, {"args": [["q", [13]], ["q", [4]]], "op": {"params": ["1.0"], "type": "CU1"}}, {"args": [["q", [12]]], "op": {"type": "H"}}, {"args": [["q", [17]], ["q", [4]]], "op": {"params": ["1.0"], "type": "CU1"}}, {"args": [["q", [4]]], "op": {"type": "H"}}, {"args": [["q", [4]]], "op": {"params": ["-0.739158712741068"], "type": "Rz"}}, {"args": [["q", [4]]], "op": {"type": "H"}}, {"args": [["q", [5]], ["q", [4]]], "op": {"params": ["1.0"], "type": "CU1"}}, {"args": [["q", [6]], ["q", [4]]], "op": {"params": ["1.0"], "type": "CU1"}}, {"args": [["q", [5]]], "op": {"type": "H"}}, {"args": [["q", [11]], ["q", [4]]], "op": {"params": ["1.0"], "type": "CU1"}}, {"args": [["q", [5]]], "op": {"params": ["-0.5"], "type": "Rz"}}, {"args": [["q", [6]]], "op": {"type": "H"}}, {"args": [["q", [5]], ["q", [2]]], "op": {"params": ["1.0"], "type": "CU1"}}, {"args": [["q", [13]], ["q", [4]]], "op": {"params": ["1.0"], "type": "CU1"}}, {"args": [["q", [6]]], "op": {"params": ["0.5"], "type": "Rz"}}, {"args": [["q", [14]], ["q", [4]]], "op": {"params": ["1.0"], "type": "CU1"}}, {"args": [["q", [13]]], "op": {"type": "H"}}, {"args": [["q", [16]], ["q", [4]]], "op": {"params": ["1.0"], "type": "CU1"}}, {"args": [["q", [14]]], "op": {"type": "H"}}, {"args": [["q", [3]], ["q", [4]]], "op": {"params": ["1.0"], "type": "CU1"}}, {"args": [["q", [16]]], "op": {"type": "H"}}, {"args": [["q", [0]], ["q", [4]]], "op": {"params": ["1.0"], "type": "CU1"}}, {"args": [["q", [3]]], "op": {"type": "H"}}, {"args": [["q", [12]], ["q", [16]]], "op": {"params": ["1.0"], "type": "CU1"}}, {"args": [["q", [0]]], "op": {"type": "H"}}, {"args": [["q", [3]]], "op": {"params": ["-1.5"], "type": "Rz"}}, {"args": [["q", [12]], ["q", [14]]], "op": {"params": ["1.0"], "type": "CU1"}}, {"args": [["q", [16]]], "op": {"type": "H"}}, {"args": [["q", [3]], ["q", [10]]], "op": {"params": ["1.0"], "type": "CU1"}}, {"args": [["q", [12]], ["q", [13]]], "op": {"params": ["1.0"], "type": "CU1"}}, {"args": [["q", [14]]], "op": {"type": "H"}}, {"args": [["q", [16]]], "op": {"params": ["1.0"], "type": "Rz"}}, {"args": [["q", [3]], ["q", [8]]], "op": {"params": ["1.0"], "type": "CU1"}}, {"args": [["q", [14]]], "op": {"params": ["1.0"], "type": "Rz"}}, {"args": [["q", [16]]], "op": {"type": "H"}}, {"args": [["q", [3]]], "op": {"type": "H"}}, {"args": [["q", [8]]], "op": {"type": "H"}}, {"args": [["q", [14]]], "op": {"type": "H"}}, {"args": [["q", [3]]], "op": {"params": ["-1.5"], "type": "Rz"}}, {"args": [["q", [3]], ["q", [7]]], "op": {"params": ["1.0"], "type": "CU1"}}, {"args": [["q", [3]]], "op": {"type": "H"}}, {"args": [["q", [7]]], "op": {"type": "H"}}, {"args": [["q", [3]]], "op": {"params": ["0.5"], "type": "Rz"}}, {"args": [["q", [11]], ["q", [7]]], "op": {"params": ["1.0"], "type": "CU1"}}, {"args": [["q", [3]], ["q", [4]]], "op": {"params": ["1.0"], "type": "CU1"}}, {"args": [["q", [7]]], "op": {"type": "H"}}, {"args": [["q", [7]], ["q", [2]]], "op": {"params": ["1.0"], "type": "CU1"}}, {"args": [["q", [3]]], "op": {"type": "H"}}, {"args": [["q", [4]]], "op": {"type": "H"}}, {"args": [["q", [13]], ["q", [2]]], "op": {"params": ["1.0"], "type": "CU1"}}, {"args": [["q", [3]]], "op": {"params": ["0.5"], "type": "Rz"}}, {"args": [["q", [4]]], "op": {"params": ["0.5"], "type": "Rz"}}, {"args": [["q", [2]]], "op": {"type": "H"}}, {"args": [["q", [2]], ["q", [14]]], "op": {"params": ["1.0"], "type": "CU1"}}, {"args": [["q", [14]]], "op": {"type": "H"}}, {"args": [["q", [14]]], "op": {"params": ["-5/2"], "type": "Rz"}}, {"args": [["q", [14]], ["q", [12]]], "op": {"params": ["1.0"], "type": "CU1"}}, {"args": [["q", [12]]], "op": {"type": "H"}}, {"args": [["q", [17]], ["q", [14]]], "op": {"params": ["1.0"], "type": "CU1"}}, {"args": [["q", [12]], ["q", [6]]], "op": {"params": ["1.0"], "type": "CU1"}}, {"args": [["q", [14]]], "op": {"type": "H"}}, {"args": [["q", [6]]], "op": {"type": "H"}}, {"args": [["q", [14]], ["q", [9]]], "op": {"params": ["1.0"], "type": "CU1"}}, {"args": [["q", [6]]], "op": {"params": ["-0.0365036381767516"], "type": "Rz"}}, {"args": [["q", [9]]], "op": {"type": "H"}}, {"args": [["q", [6]]], "op": {"type": "H"}}, {"args": [["q", [9]], ["q", [8]]], "op": {"params": ["1.0"], "type": "CU1"}}, {"args": [["q", [12]], ["q", [6]]], "op": {"params": ["1.0"], "type": "CU1"}}, {"args": [["q", [8]]], "op": {"type": "H"}}, {"args": [["q", [8]], ["q", [4]]], "op": {"params": ["1.0"], "type": "CU1"}}, {"args": [["q", [6]]], "op": {"type": "H"}}, {"args": [["q", [12]]], "op": {"type": "H"}}, {"args": [["q", [4]]], "op": {"type": "H"}}, {"args": [["q", [12]]], "op": {"params": ["2.5"], "type": "Rz"}}, {"args": [["q", [4]], ["q", [3]]], "op": {"params": ["1.0"], "type": "CU1"}}, {"args": [["q", [3]]], "op": {"type": "H"}}, {"args": [["q", [3]], ["q", [1]]], "op": {"params": ["1.0"], "type": "CU1"}}, {"args": [["q", [1]]], "op": {"type": "H"}}, {"args": [["q", [1]], ["q", [0]]], "op": {"params": ["1.0"], "type": "CU1"}}, {"args": [["q", [0]]], "op": {"type": "H"}}, {"args": [["q", [0]]], "op": {"params": ["-0.246383794586645"], "type": "Rz"}}, {"args": [["q", [0]]], "op": {"type": "H"}}, {"args": [["q", [1]], ["q", [0]]], "op": {"params": ["1.0"], "type": "CU1"}}, {"args": [["q", [6]], ["q", [0]]], "op": {"params": ["1.0"], "type": "CU1"}}, {"args": [["q", [1]]], "op": {"type": "H"}}, {"args": [["q", [3]], ["q", [1]]], "op": {"params": ["1.0"], "type": "CU1"}}, {"args": [["q", [3]]], "op": {"type": "H"}}, {"args": [["q", [4]], ["q", [3]]], "op": {"params": ["1.0"], "type": "CU1"}}, {"args": [["q", [4]]], "op": {"type": "H"}}, {"args": [["q", [8]], ["q", [4]]], "op": {"params": ["1.0"], "type": "CU1"}}, {"args": [["q", [4]], ["q", [3]]], "op": {"params": ["1.0"], "type": "CU1"}}, {"args": [["q", [8]]], "op": {"type": "H"}}, {"args": [["q", [3]]], "op": {"type": "H"}}, {"args": [["q", [9]], ["q", [8]]], "op": {"params": ["1.0"], "type": "CU1"}}, {"args": [["q", [15]], ["q", [8]]], "op": {"params": ["1.0"], "type": "CU1"}}, {"args": [["q", [9]]], "op": {"type": "H"}}, {"args": [["q", [8]]], "op": {"type": "H"}}, {"args": [["q", [14]], ["q", [9]]], "op": {"params": ["1.0"], "type": "CU1"}}, {"args": [["q", [9]]], "op": {"type": "H"}}, {"args": [["q", [14]]], "op": {"type": "H"}}, {"args": [["q", [9]]], "op": {"params": ["-1.5"], "type": "Rz"}}, {"args": [["q", [14]]], "op": {"params": ["2.5"], "type": "Rz"}}, {"args": [["q", [17]], ["q", [14]]], "op": {"params": ["1.0"], "type": "CU1"}}, {"args": [["q", [14]], ["q", [12]]], "op": {"params": ["1.0"], "type": "CU1"}}, {"args": [["q", [12]], ["q", [10]]], "op": {"params": ["1.0"], "type": "CU1"}}, {"args": [["q", [14]]], "op": {"type": "H"}}, {"args": [["q", [10]]], "op": {"type": "H"}}, {"args": [["q", [14]]], "op": {"params": ["-1.5"], "type": "Rz"}}, {"args": [["q", [2]], ["q", [14]]], "op": {"params": ["1.0"], "type": "CU1"}}, {"args": [["q", [2]]], "op": {"type": "H"}}, {"args": [["q", [14]]], "op": {"type": "H"}}, {"args": [["q", [13]], ["q", [2]]], "op": {"params": ["1.0"], "type": "CU1"}}, {"args": [["q", [14]]], "op": {"params": ["3"], "type": "Rz"}}, {"args": [["q", [7]], ["q", [2]]], "op": {"params": ["1.0"], "type": "CU1"}}, {"args": [["q", [14]], ["q", [9]]], "op": {"params": ["1.0"], "type": "CU1"}}, {"args": [["q", [13]]], "op": {"type": "H"}}, {"args": [["q", [5]], ["q", [2]]], "op": {"params": ["1.0"], "type": "CU1"}}, {"args": [["q", [7]]], "op": {"type": "H"}}, {"args": [["q", [10]], ["q", [9]]], "op": {"params": ["1.0"], "type": "CU1"}}, {"args": [["q", [13]]], "op": {"params": ["-1.5"], "type": "Rz"}}, {"args": [["q", [2]]], "op": {"type": "H"}}, {"args": [["q", [5]]], "op": {"type": "H"}}, {"args": [["q", [11]], ["q", [7]]], "op": {"params": ["1.0"], "type": "CU1"}}, {"args": [["q", [9]]], "op": {"type": "H"}}, {"args": [["q", [2]]], "op": {"params": ["4.5"], "type": "Rz"}}, {"args": [["q", [7]]], "op": {"type": "H"}}, {"args": [["q", [2]], ["q", [1]]], "op": {"params": ["1.0"], "type": "CU1"}}, {"args": [["q", [7]]], "op": {"params": ["0.5"], "type": "Rz"}}, {"args": [["q", [3]], ["q", [1]]], "op": {"params": ["1.0"], "type": "CU1"}}, {"args": [["q", [17]], ["q", [7]]], "op": {"params": ["1.0"], "type": "CU1"}}, {"args": [["q", [8]], ["q", [7]]], "op": {"params": ["1.0"], "type": "CU1"}}, {"args": [["q", [9]], ["q", [7]]], "op": {"params": ["1.0"], "type": "CU1"}}, {"args": [["q", [7]]], "op": {"type": "H"}}, {"args": [["q", [7]], ["q", [1]]], "op": {"params": ["1.0"], "type": "CU1"}}, {"args": [["q", [1]]], "op": {"type": "H"}}, {"args": [["q", [1]]], "op": {"params": ["-0.969796240173155"], "type": "Rz"}}, {"args": [["q", [1]]], "op": {"type": "H"}}, {"args": [["q", [7]], ["q", [1]]], "op": {"params": ["1.0"], "type": "CU1"}}, {"args": [["q", [3]], ["q", [1]]], "op": {"params": ["1.0"], "type": "CU1"}}, {"args": [["q", [7]]], "op": {"type": "H"}}, {"args": [["q", [2]], ["q", [1]]], "op": {"params": ["1.0"], "type": "CU1"}}, {"args": [["q", [3]]], "op": {"type": "H"}}, {"args": [["q", [7]]], "op": {"params": ["3.5"], "type": "Rz"}}, {"args": [["q", [1]]], "op": {"type": "H"}}, {"args": [["q", [4]], ["q", [3]]], "op": {"params": ["1.0"], "type": "CU1"}}, {"args": [["q", [9]], ["q", [7]]], "op": {"params": ["1.0"], "type": "CU1"}}, {"args": [["q", [1]]], "op": {"params": ["0.5"], "type": "Rz"}}, {"args": [["q", [3]]], "op": {"type": "H"}}, {"args": [["q", [4]]], "op": {"type": "H"}}, {"args": [["q", [8]], ["q", [7]]], "op": {"params": ["1.0"], "type": "CU1"}}, {"args": [["q", [9]]], "op": {"type": "H"}}, {"args": [["q", [3]]], "op": {"params": ["0.5"], "type": "Rz"}}, {"args": [["q", [17]], ["q", [7]]], "op": {"params": ["1.0"], "type": "CU1"}}, {"args": [["q", [8]]], "op": {"type": "H"}}, {"args": [["q", [10]], ["q", [9]]], "op": {"params": ["1.0"], "type": "CU1"}}, {"args": [["q", [7]]], "op": {"type": "H"}}, {"args": [["q", [8]]], "op": {"params": ["1.5"], "type": "Rz"}}, {"args": [["q", [14]], ["q", [9]]], "op": {"params": ["1.0"], "type": "CU1"}}, {"args": [["q", [10]]], "op": {"type": "H"}}, {"args": [["q", [11]], ["q", [7]]], "op": {"params": ["1.0"], "type": "CU1"}}, {"args": [["q", [15]], ["q", [8]]], "op": {"params": ["1.0"], "type": "CU1"}}, {"args": [["q", [9]]], "op": {"type": "H"}}, {"args": [["q", [10]]], "op": {"params": ["-0.5"], "type": "Rz"}}, {"args": [["q", [14]]], "op": {"type": "H"}}, {"args": [["q", [7]]], "op": {"type": "H"}}, {"args": [["q", [8]]], "op": {"type": "H"}}, {"args": [["q", [12]], ["q", [10]]], "op": {"params": ["1.0"], "type": "CU1"}}, {"args": [["q", [14]]], "op": {"params": ["0.5"], "type": "Rz"}}, {"args": [["q", [7]], ["q", [0]]], "op": {"params": ["1.0"], "type": "CU1"}}, {"args": [["q", [8]]], "op": {"params": ["-0.5"], "type": "Rz"}}, {"args": [["q", [10]]], "op": {"type": "H"}}, {"args": [["q", [12]]], "op": {"type": "H"}}, {"args": [["q", [15]], ["q", [14]]], "op": {"params": ["1.0"], "type": "CU1"}}, {"args": [["q", [8]], ["q", [4]]], "op": {"params": ["1.0"], "type": "CU1"}}, {"args": [["q", [12]]], "op": {"params": ["-1.5"], "type": "Rz"}}, {"args": [["q", [14]]], "op": {"type": "H"}}, {"args": [["q", [13]], ["q", [12]]], "op": {"params": ["1.0"], "type": "CU1"}}, {"args": [["q", [17]], ["q", [12]]], "op": {"params": ["1.0"], "type": "CU1"}}, {"args": [["q", [12]]], "op": {"type": "H"}}, {"args": [["q", [12]], ["q", [0]]], "op": {"params": ["1.0"], "type": "CU1"}}, {"args": [["q", [0]]], "op": {"type": "H"}}, {"args": [["q", [0]], ["q", [16]]], "op": {"params": ["1.0"], "type": "CU1"}}, {"args": [["q", [16]]], "op": {"type": "H"}}, {"args": [["q", [16]]], "op": {"params": ["-1/2"], "type": "Rz"}}, {"args": [["q", [16]], ["q", [9]]], "op": {"params": ["1.0"], "type": "CU1"}}, {"args": [["q", [14]], ["q", [9]]], "op": {"params": ["1.0"], "type": "CU1"}}, {"args": [["q", [16]]], "op": {"type": "H"}}, {"args": [["q", [9]]], "op": {"type": "H"}}, {"args": [["q", [16]], ["q", [10]]], "op": {"params": ["1.0"], "type": "CU1"}}, {"args": [["q", [9]], ["q", [4]]], "op": {"params": ["1.0"], "type": "CU1"}}, {"args": [["q", [10]]], "op": {"type": "H"}}, {"args": [["q", [4]]], "op": {"type": "H"}}, {"args": [["q", [10]], ["q", [8]]], "op": {"params": ["1.0"], "type": "CU1"}}, {"args": [["q", [4]], ["q", [3]]], "op": {"params": ["1.0"], "type": "CU1"}}, {"args": [["q", [8]]], "op": {"type": "H"}}, {"args": [["q", [8]], ["q", [1]]], "op": {"params": ["1.0"], "type": "CU1"}}, {"args": [["q", [3]]], "op": {"type": "H"}}, {"args": [["q", [1]]], "op": {"type": "H"}}, {"args": [["q", [3]], ["q", [2]]], "op": {"params": ["1.0"], "type": "CU1"}}, {"args": [["q", [1]]], "op": {"params": ["-0.423264925740336"], "type": "Rz"}}, {"args": [["q", [2]]], "op": {"type": "H"}}, {"args": [["q", [1]]], "op": {"type": "H"}}, {"args": [["q", [2]]], "op": {"params": ["-0.654255901044602"], "type": "Rz"}}, {"args": [["q", [1]]], "op": {"params": ["-0.5"], "type": "Rz"}}, {"args": [["q", [2]]], "op": {"type": "H"}}, {"args": [["q", [8]], ["q", [1]]], "op": {"params": ["1.0"], "type": "CU1"}}, {"args": [["q", [3]], ["q", [2]]], "op": {"params": ["1.0"], "type": "CU1"}}, {"args": [["q", [1]]], "op": {"type": "H"}}, {"args": [["q", [2]]], "op": {"type": "H"}}, {"args": [["q", [3]]], "op": {"type": "H"}}, {"args": [["q", [8]]], "op": {"type": "H"}}, {"args": [["q", [2]]], "op": {"params": ["2.5"], "type": "Rz"}}, {"args": [["q", [4]], ["q", [3]]], "op": {"params": ["1.0"], "type": "CU1"}}, {"args": [["q", [8]]], "op": {"params": ["2.5"], "type": "Rz"}}, {"args": [["q", [4]]], "op": {"type": "H"}}, {"args": [["q", [10]], ["q", [8]]], "op": {"params": ["1.0"], "type": "CU1"}}, {"args": [["q", [4]]], "op": {"params": ["4.5"], "type": "Rz"}}, {"args": [["q", [10]]], "op": {"type": "H"}}, {"args": [["q", [9]], ["q", [4]]], "op": {"params": ["1.0"], "type": "CU1"}}, {"args": [["q", [16]], ["q", [10]]], "op": {"params": ["1.0"], "type": "CU1"}}, {"args": [["q", [8]], ["q", [4]]], "op": {"params": ["1.0"], "type": "CU1"}}, {"args": [["q", [9]]], "op": {"type": "H"}}, {"args": [["q", [16]]], "op": {"type": "H"}}, {"args": [["q", [4]], ["q", [3]]], "op": {"params": ["1.0"], "type": "CU1"}}, {"args": [["q", [8]]], "op": {"type": "H"}}, {"args": [["q", [14]], ["q", [9]]], "op": {"params": ["1.0"], "type": "CU1"}}, {"args": [["q", [16]]], "op": {"params": ["1/2"], "type": "Rz"}}, {"args": [["q", [3]]], "op": {"type": "H"}}, {"args": [["q", [8]]], "op": {"params": ["-1.5"], "type": "Rz"}}, {"args": [["q", [16]], ["q", [9]]], "op": {"params": ["1.0"], "type": "CU1"}}, {"args": [["q", [14]]], "op": {"type": "H"}}, {"args": [["q", [9]]], "op": {"type": "H"}}, {"args": [["q", [15]], ["q", [14]]], "op": {"params": ["1.0"], "type": "CU1"}}, {"args": [["q", [16]]], "op": {"type": "H"}}, {"args": [["q", [0]], ["q", [16]]], "op": {"params": ["1.0"], "type": "CU1"}}, {"args": [["q", [14]]], "op": {"type": "H"}}, {"args": [["q", [15]]], "op": {"type": "H"}}, {"args": [["q", [0]]], "op": {"type": "H"}}, {"args": [["q", [14]], ["q", [8]]], "op": {"params": ["1.0"], "type": "CU1"}}, {"args": [["q", [15]]], "op": {"params": ["0.5"], "type": "Rz"}}, {"args": [["q", [16]]], "op": {"type": "H"}}, {"args": [["q", [12]], ["q", [0]]], "op": {"params": ["1.0"], "type": "CU1"}}, {"args": [["q", [16]]], "op": {"params": ["-1.0"], "type": "Rz"}}, {"args": [["q", [7]], ["q", [0]]], "op": {"params": ["1.0"], "type": "CU1"}}, {"args": [["q", [12]]], "op": {"type": "H"}}, {"args": [["q", [16]]], "op": {"type": "H"}}, {"args": [["q", [6]], ["q", [0]]], "op": {"params": ["1.0"], "type": "CU1"}}, {"args": [["q", [7]]], "op": {"type": "H"}}, {"args": [["q", [17]], ["q", [12]]], "op": {"params": ["1.0"], "type": "CU1"}}, {"args": [["q", [0]]], "op": {"type": "H"}}, {"args": [["q", [6]]], "op": {"type": "H"}}, {"args": [["q", [11]], ["q", [7]]], "op": {"params": ["1.0"], "type": "CU1"}}, {"args": [["q", [13]], ["q", [12]]], "op": {"params": ["1.0"], "type": "CU1"}}, {"args": [["q", [0]]], "op": {"params": ["0.5"], "type": "Rz"}}, {"args": [["q", [17]], ["q", [7]]], "op": {"params": ["1.0"], "type": "CU1"}}, {"args": [["q", [11]]], "op": {"type": "H"}}, {"args": [["q", [13]]], "op": {"type": "H"}}, {"args": [["q", [2]], ["q", [0]]], "op": {"params": ["1.0"], "type": "CU1"}}, {"args": [["q", [7]]], "op": {"type": "H"}}, {"args": [["q", [11]]], "op": {"params": ["-1.5"], "type": "Rz"}}, {"args": [["q", [13]]], "op": {"params": ["0.5"], "type": "Rz"}}, {"args": [["q", [3]], ["q", [0]]], "op": {"params": ["1.0"], "type": "CU1"}}, {"args": [["q", [7]], ["q", [5]]], "op": {"params": ["1.0"], "type": "CU1"}}, {"args": [["q", [11]], ["q", [9]]], "op": {"params": ["1.0"], "type": "CU1"}}, {"args": [["q", [9]]], "op": {"type": "H"}}, {"args": [["q", [9]], ["q", [8]]], "op": {"params": ["1.0"], "type": "CU1"}}, {"args": [["q", [8]]], "op": {"type": "H"}}, {"args": [["q", [8]], ["q", [5]]], "op": {"params": ["1.0"], "type": "CU1"}}, {"args": [["q", [5]]], "op": {"type": "H"}}, {"args": [["q", [5]], ["q", [0]]], "op": {"params": ["1.0"], "type": "CU1"}}, {"args": [["q", [0]]], "op": {"type": "H"}}, {"args": [["q", [0]]], "op": {"params": ["0.837034417510696"], "type": "Rz"}}, {"args": [["q", [0]]], "op": {"type": "H"}}, {"args": [["q", [0]]], "op": {"params": ["3.5"], "type": "Rz"}}, {"args": [["q", [5]], ["q", [0]]], "op": {"params": ["1.0"], "type": "CU1"}}, {"args": [["q", [3]], ["q", [0]]], "op": {"params": ["1.0"], "type": "CU1"}}, {"args": [["q", [5]]], "op": {"type": "H"}}, {"args": [["q", [2]], ["q", [0]]], "op": {"params": ["1.0"], "type": "CU1"}}, {"args": [["q", [3]]], "op": {"type": "H"}}, {"args": [["q", [8]], ["q", [5]]], "op": {"params": ["1.0"], "type": "CU1"}}, {"args": [["q", [0]]], "op": {"type": "H"}}, {"args": [["q", [2]]], "op": {"type": "H"}}, {"args": [["q", [3]]], "op": {"params": ["-0.5"], "type": "Rz"}}, {"args": [["q", [7]], ["q", [5]]], "op": {"params": ["1.0"], "type": "CU1"}}, {"args": [["q", [8]]], "op": {"type": "H"}}, {"args": [["q", [2]]], "op": {"params": ["0.5"], "type": "Rz"}}, {"args": [["q", [4]], ["q", [3]]], "op": {"params": ["1.0"], "type": "CU1"}}, {"args": [["q", [7]]], "op": {"type": "H"}}, {"args": [["q", [9]], ["q", [8]]], "op": {"params": ["1.0"], "type": "CU1"}}, {"args": [["q", [3]]], "op": {"type": "H"}}, {"args": [["q", [4]]], "op": {"type": "H"}}, {"args": [["q", [17]], ["q", [7]]], "op": {"params": ["1.0"], "type": "CU1"}}, {"args": [["q", [14]], ["q", [8]]], "op": {"params": ["1.0"], "type": "CU1"}}, {"args": [["q", [9]]], "op": {"type": "H"}}, {"args": [["q", [4]]], "op": {"params": ["0.5"], "type": "Rz"}}, {"args": [["q", [9]]], "op": {"params": ["-0.5"], "type": "Rz"}}, {"args": [["q", [14]]], "op": {"type": "H"}}, {"args": [["q", [17]]], "op": {"type": "H"}}, {"args": [["q", [11]], ["q", [9]]], "op": {"params": ["1.0"], "type": "CU1"}}, {"args": [["q", [9]]], "op": {"type": "H"}}, {"args": [["q", [11]]], "op": {"type": "H"}}, {"args": [["q", [11]]], "op": {"params": ["0.5"], "type": "Rz"}}], "created_qubits": [], "discarded_qubits": [], "implicit_permutation": [[["q", [0]], ["q", [0]]], [["q", [1]], ["q", [1]]], [["q", [2]], ["q", [2]]], [["q", [3]], ["q", [3]]], [["q", [4]], ["q", [4]]], [["q", [5]], ["q", [5]]], [["q", [6]], ["q", [6]]], [["q", [7]], ["q", [7]]], [["q", [8]], ["q", [8]]], [["q", [9]], ["q", [9]]], [["q", [10]], ["q", [10]]], [["q", [11]], ["q", [11]]], [["q", [12]], ["q", [12]]], [["q", [13]], ["q", [13]]], [["q", [14]], ["q", [14]]], [["q", [15]], ["q", [15]]], [["q", [16]], ["q", [16]]], [["q", [17]], ["q", [17]]]], "phase": "1.0", "qubits": [["q", [0]], ["q", [1]], ["q", [2]], ["q", [3]], ["q", [4]], ["q", [5]], ["q", [6]], ["q", [7]], ["q", [8]], ["q", [9]], ["q", [10]], ["q", [11]], ["q", [12]], ["q", [13]], ["q", [14]], ["q", [15]], ["q", [16]], ["q", [17]]]}}, "placement": {"0": 0, "33": 0, "35": 0, "67": 0, "68": 0, "113": 0, "121": 0, "123": 0, "124": 0, "125": 0, "126": 0, "130": 0, "146": 0, "148": 0, "149": 0, "150": 0, "151": 0, "205": 0, "233": 0, "254": 0, "255": 0, "256": 2, "292": 2, "297": 2, "298": 1, "318": 1, "320": 2, "321": 2, "322": 2, "327": 0, "328": 0, "333": 0, "334": 0, "335": 0, "336": 0, "1": 0, "18": 1, "21": 1, "22": 1, "23": 1, "47": 1, "48": 0, "49": 1, "50": 1, "66": 0, "69": 0, "88": 0, "90": 0, "97": 0, "98": 0, "99": 0, "100": 0, "176": 0, "178": 0, "253": 0, "257": 0, "274": 0, "275": 0, "279": 0, "280": 0, "281": 0, "282": 0, "305": 0, "307": 0, "2": 0, "20": 0, "31": 0, "34": 0, "40": 0, "64": 0, "70": 0, "83": 0, "107": 0, "188": 0, "206": 0, "228": 0, "242": 2, "243": 2, "244": 1, "267": 1, "268": 2, "269": 2, "271": 0, "306": 0, "308": 0, "3": 0, "29": 0, "36": 0, "41": 0, "58": 0, "62": 0, "72": 0, "84": 0, "86": 0, "102": 0, "104": 0, "118": 0, "127": 0, "134": 0, "143": 0, "153": 0, "155": 0, "162": 2, "174": 0, "177": 0, "185": 0, "186": 0, "189": 1, "198": 1, "199": 1, "207": 0, "232": 0, "236": 1, "238": 1, "239": 1, "241": 0, "252": 0, "258": 0, "260": 0, "283": 0, "304": 0, "309": 0, "314": 0, "339": 0, "4": 2, "32": 2, "37": 2, "63": 2, "71": 2, "80": 2, "108": 2, "114": 2, "132": 2, "139": 1, "158": 1, "200": 1, "201": 2, "202": 1, "203": 1, "204": 1, "208": 1, "209": 1, "210": 2, "211": 1, "212": 2, "213": 1, "214": 1, "215": 1, "216": 1, "217": 2, "218": 1, "219": 1, "220": 1, "221": 2, "222": 2, "223": 1, "224": 2, "225": 2, "226": 1, "227": 1, "229": 1, "230": 1, "231": 1, "251": 2, "259": 2, "294": 2, "302": 2, "311": 2, "313": 0, "5": 0, "30": 0, "38": 0, "53": 1, "56": 1, "65": 1, "74": 1, "92": 1, "94": 1, "96": 1, "101": 1, "103": 1, "105": 1, "137": 1, "145": 1, "147": 1, "152": 1, "154": 1, "156": 1, "175": 0, "180": 0, "329": 0, "332": 0, "337": 0, "338": 0, "6": 1, "61": 1, "73": 1, "78": 1, "109": 1, "115": 1, "119": 1, "122": 1, "128": 1, "129": 1, "131": 1, "141": 1, "159": 1, "172": 1, "179": 1, "247": 1, "250": 1, "7": 1, "60": 1, "75": 1, "91": 1, "95": 1, "106": 1, "110": 1, "116": 1, "135": 1, "142": 1, "144": 1, "157": 1, "160": 1, "170": 1, "181": 1, "240": 1, "273": 1, "276": 1, "277": 1, "278": 1, "284": 1, "285": 1, "286": 1, "289": 1, "324": 1, "326": 1, "341": 1, "8": 1, "43": 1, "51": 1, "52": 1, "54": 1, "81": 1, "82": 1, "85": 1, "87": 1, "93": 1, "111": 1, "140": 1, "161": 1, "164": 1, "165": 1, "166": 1, "192": 1, "194": 1, "195": 1, "249": 1, "261": 1, "262": 1, "290": 1, "303": 1, "310": 1, "319": 1, "331": 1, "340": 1, "342": 1, "9": 2, "27": 2, "44": 2, "59": 2, "76": 2, "117": 1, "120": 1, "133": 1, "136": 1, "173": 2, "182": 2, "248": 2, "263": 2, "270": 2, "272": 2, "287": 2, "288": 2, "299": 1, "300": 1, "315": 1, "316": 1, "330": 2, "343": 2, "10": 1, "28": 1, "39": 1, "112": 1, "138": 1, "266": 1, "291": 1, "301": 1, "312": 1, "11": 2, "25": 2, "42": 2, "57": 2, "77": 2, "171": 2, "184": 2, "12": 2, "26": 2, "45": 2, "168": 2, "183": 2, "190": 1, "193": 1, "197": 1, "234": 1, "235": 1, "237": 2, "245": 1, "265": 1, "295": 2, "296": 2, "323": 2, "325": 2, "13": 1, "19": 1, "89": 1, "169": 1, "187": 1, "14": 1, "24": 1, "46": 1, "55": 1, "79": 1, "167": 1, "191": 1, "246": 1, "264": 1, "293": 1, "317": 1, "15": 1, "16": 1, "163": 1, "196": 1, "17": 2}, "network": {"server_coupling": [[0, 1], [0, 2], [1, 2]], "server_qubits": {"0": [0, 3, 12, 13, 17], "1": [1, 4, 5, 7, 9, 14, 15, 16], "2": [2, 6, 8, 10, 11]}, "server_ebit_mem": {"0": 5, "1": 5, "2": 5}}}